{
  "noiseKey": {
    "private": {
      "type": "Buffer",
      "data": [
        112,
        133,
        91,
        179,
        175,
        192,
        9,
        228,
        57,
        62,
        99,
        98,
        135,
        208,
        226,
        22,
        227,
        15,
        18,
        193,
        67,
        26,
        120,
        249,
        204,
        163,
        136,
        180,
        119,
        45,
        186,
        123
      ]
    },
    "public": {
      "type": "Buffer",
      "data": [
        187,
        20,
        245,
        68,
        127,
        239,
        55,
        165,
        147,
        157,
        153,
        226,
        179,
        158,
        180,
        168,
        99,
        106,
        199,
        35,
        117,
        144,
        201,
        121,
        35,
        72,
        90,
        45,
        218,
        88,
        9,
        119
      ]
    }
  },
  "pairingEphemeralKeyPair": {
    "private": {
      "type": "Buffer",
      "data": [
        136,
        54,
        12,
        217,
        42,
        109,
        90,
        233,
        18,
        16,
        50,
        89,
        96,
        105,
        21,
        247,
        192,
        209,
        208,
        172,
        183,
        180,
        224,
        140,
        66,
        162,
        192,
        157,
        194,
        229,
        8,
        76
      ]
    },
    "public": {
      "type": "Buffer",
      "data": [
        237,
        72,
        123,
        208,
        114,
        78,
        80,
        138,
        139,
        142,
        12,
        200,
        96,
        124,
        245,
        52,
        6,
        213,
        88,
        71,
        134,
        149,
        219,
        162,
        118,
        142,
        113,
        161,
        189,
        69,
        147,
        24
      ]
    }
  },
  "signedIdentityKey": {
    "private": {
      "type": "Buffer",
      "data": [
        56,
        56,
        60,
        244,
        73,
        234,
        173,
        220,
        148,
        80,
        231,
        215,
        150,
        195,
        217,
        234,
        158,
        41,
        91,
        122,
        248,
        255,
        103,
        206,
        63,
        101,
        51,
        94,
        55,
        165,
        235,
        65
      ]
    },
    "public": {
      "type": "Buffer",
      "data": [
        245,
        210,
        214,
        130,
        137,
        167,
        66,
        198,
        147,
        54,
        164,
        203,
        0,
        86,
        234,
        182,
        207,
        139,
        199,
        104,
        8,
        213,
        126,
        243,
        112,
        208,
        243,
        205,
        47,
        134,
        14,
        3
      ]
    }
  },
  "signedPreKey": {
    "keyPair": {
      "private": {
        "type": "Buffer",
        "data": [
          128,
          94,
          213,
          70,
          249,
          228,
          233,
          56,
          31,
          141,
          6,
          169,
          13,
          235,
          158,
          105,
          2,
          197,
          189,
          20,
          231,
          50,
          104,
          233,
          178,
          70,
          145,
          239,
          124,
          113,
          219,
          114
        ]
      },
      "public": {
        "type": "Buffer",
        "data": [
          231,
          219,
          40,
          242,
          152,
          54,
          86,
          87,
          104,
          171,
          66,
          187,
          237,
          198,
          212,
          213,
          18,
          164,
          62,
          71,
          231,
          10,
          92,
          36,
          225,
          178,
          16,
          132,
          205,
          3,
          12,
          102
        ]
      }
    },
    "signature": {
      "type": "Buffer",
      "data": [
        21,
        227,
        95,
        229,
        84,
        237,
        72,
        176,
        171,
        46,
        16,
        204,
        84,
        101,
        175,
        182,
        61,
        100,
        107,
        177,
        47,
        94,
        119,
        152,
        11,
        155,
        136,
        105,
        158,
        185,
        63,
        243,
        145,
        212,
        208,
        109,
        69,
        233,
        109,
        10,
        144,
        214,
        212,
        22,
        214,
        230,
        191,
        185,
        101,
        235,
        79,
        27,
        18,
        254,
        179,
        117,
        241,
        116,
        246,
        231,
        177,
        225,
        172,
        14
      ]
    },
    "keyId": 1
  },
  "registrationId": 0,
  "advSecretKey": "ZuY+dPPArypriVDwbN8oQ/2vnffvR+Ew8WTajR6tF4E=",
  "processedHistoryMessages": [],
  "nextPreKeyId": 31,
  "firstUnuploadedPreKeyId": 31,
  "accountSyncCounter": 0,
  "accountSettings": {
    "unarchiveChats": false
  },
  "registered": true,
  "pairingCode": "DK63E4PV",
  "me": {
    "id": "94773010580:36@s.whatsapp.net",
    "name": "_____________\n\n𝐅\n𝐄\n𝐍\n𝐈\n𝐗\n_____________\n\n𝐈\n𝐃\n𝐎\n𝐖\n𝐍\n𝐄\n𝐑",
    "lid": "200914795282588:36@lid"
  },
  "account": {
    "details": "CJaAvPUBEIWilb4GGA8gACgA",
    "accountSignatureKey": "zPDTKV9HfvkB+CT+t84JMV/1MqNcpffRWKfrUBsJJGc=",
    "accountSignature": "m3rL/yyo3Ku8wvBlqG8I6klZZhFZ/IpoTTeESJda+w9AfoWLT1rVqWcQ/5spIgSZBuBwmA4CWFsGRaKQo6P3Ag==",
    "deviceSignature": "s2AkEbHzaBAvC4E7oh3VqoFU2+1NFi7wgT9zhGQr1XRhjMc+Jke6ms081DJFvSvowtx7tK5KAJJYNS3AXtN2DQ=="
  },
  "signalIdentities": [
    {
      "identifier": {
        "name": "94773010580:36@s.whatsapp.net",
        "deviceId": 0
      },
      "identifierKey": {
        "type": "Buffer",
        "data": [
          5,
          204,
          240,
          211,
          41,
          95,
          71,
          126,
          249,
          1,
          248,
          36,
          254,
          183,
          206,
          9,
          49,
          95,
          245,
          50,
          163,
          92,
          165,
          247,
          209,
          88,
          167,
          235,
          80,
          27,
          9,
          36,
          103
        ]
      }
    }
  ],
  "platform": "smba",
  "routingInfo": {
    "type": "Buffer",
    "data": [
      8,
      5,
      8,
      2
    ]
  },
  "lastAccountSyncTimestamp": 1740984585,
  "lastPropHash": "2V77qU",
  "myAppStateKeyId": "AAAAANoi"
}